{  
  "SuperAdminID": "sujt0001",
  "SuperAdminPassword": "123456789",

  "StoreAdminID": "mors0001",
  "StoreAdminPassword": "123456789",

  "StoreKeeperID": "taif0001",
  "StoreKeeperPassword": "123456789",

  "UserID": "risa0001",
  "UserPassword": "123456789",
  "UserName": "রাইসা আমিন",

  "StoreName": "SQA_CoKreates_store",

  "RequisitionReferenceNo": "REQ/2020/06/29/3334",
  "CategoryType": "কফি মেকার",
  "ItemName": "coffee maker",
  "ItemRequisitionQuantity": "1",
  "FeaturesName": "Brand",
  "FeaturesValue": "LG",

  "RequisitionComment": "অনুমোদন দেওয়া হলো।",

  "DIReferenceNo": "REQ/2020/07/02/1963",
  "DIMemoNo": "GRP/CoK/0001",
  "DIRemarks": "এটি জিআরপি এসকিউএ টিম দ্বারা অটোমেশন পরীক্ষা।",
  "ItemDescription": "Brand: samsung, Milliliter: 500ml",
  "DIQuantity": "500",
  "DIPrice": "1000"
}
